dcos_quobyte/__init__.py
dcos_quobyte/constants.py
dcos_quobyte/cli.py
dcos_quobyte-1.0.1b0.dist-info/pbr.json
dcos_quobyte-1.0.1b0.dist-info/top_level.txt
dcos_quobyte-1.0.1b0.dist-info/entry_points.txt
dcos_quobyte-1.0.1b0.dist-info/METADATA
dcos_quobyte-1.0.1b0.dist-info/DESCRIPTION.rst
dcos_quobyte-1.0.1b0.dist-info/metadata.json
dcos_quobyte-1.0.1b0.dist-info/WHEEL
dcos_quobyte-1.0.1b0.dist-info/RECORD
