Metadata-Version: 2.0
Name: dcos-quobyte
Version: 1.0.1b0
Summary: DCOS Quobyte Command Line Interface
Home-page: https://github.com/mesosphere/dcos-quobyte
Author: Quobyte GmbH
Author-email: support@quobyte.com
License: Apache License 2.0
Keywords: dcos command,quobyte,mesosphere,storage,performance,scalable
Platform: UNKNOWN
Classifier: Development Status :: 4 - Beta
Classifier: Intended Audience :: Developers
Classifier: Intended Audience :: Information Technology
Classifier: License :: OSI Approved :: Apache Software License
Classifier: Programming Language :: Python :: 2
Classifier: Programming Language :: Python :: 2.6
Classifier: Programming Language :: Python :: 2.7
Classifier: Programming Language :: Python :: 3
Classifier: Programming Language :: Python :: 3.2
Classifier: Programming Language :: Python :: 3.3
Classifier: Programming Language :: Python :: 3.4
Requires-Dist: docopt
Requires-Dist: dcos
Requires-Dist: requests
Provides-Extra: dev
Requires-Dist: check-manifest; extra == 'dev'
Provides-Extra: test
Requires-Dist: coverage; extra == 'test'
